pegaflow/__init__.py
pegaflow/_server.py
pegaflow/connector/__init__.py
pegaflow/connector/common.py
pegaflow/connector/connector_metrics.py
pegaflow/connector/scheduler.py
pegaflow/connector/state_manager.py
pegaflow/connector/worker.py
pegaflow/ipc_wrapper.py
pegaflow/logging_utils.py
pegaflow/pegaflow-server-py
pegaflow/pegaflow.cpython-312-x86_64-linux-gnu.so
pegaflow/pegaflow.pyi
pegaflow/sglang/peagflow_radix_cache.py
pegaflow_llm-0.0.12.dist-info/METADATA
pegaflow_llm-0.0.12.dist-info/WHEEL
pegaflow_llm-0.0.12.dist-info/entry_points.txt
pegaflow_llm-0.0.12.dist-info/RECORD
