Metadata-Version: 2.4
Name: pegaflow-llm
Version: 0.0.12
Classifier: Development Status :: 3 - Alpha
Classifier: Intended Audience :: Developers
Classifier: Programming Language :: Rust
Classifier: Programming Language :: Python :: 3
Classifier: Programming Language :: Python :: 3.10
Classifier: Programming Language :: Python :: 3.11
Classifier: Programming Language :: Python :: 3.12
Classifier: Programming Language :: Python :: Implementation :: CPython
Requires-Dist: pegaflow-llm[test] ; extra == 'dev'
Requires-Dist: ruff>=0.4 ; extra == 'dev'
Requires-Dist: mypy>=1.10 ; extra == 'dev'
Requires-Dist: pytest>=8.0 ; extra == 'test'
Requires-Dist: pytest-cov>=4.0 ; extra == 'test'
Requires-Dist: pytest-xdist>=3.0 ; extra == 'test'
Requires-Dist: datasets>=2.0 ; extra == 'test'
Requires-Dist: numpy>=1.24 ; extra == 'test'
Provides-Extra: dev
Provides-Extra: test
Summary: High-performance key-value storage engine with Python bindings
Keywords: storage,kv-store,rust,vllm,inference
Author: PegaFlow Contributors
License: MIT
Requires-Python: >=3.10
